setup.py
rdsutilspack/__init__.py
rdsutilspack/__main__.py
rdsutilspack.egg-info/PKG-INFO
rdsutilspack.egg-info/SOURCES.txt
rdsutilspack.egg-info/dependency_links.txt
rdsutilspack.egg-info/entry_points.txt
rdsutilspack.egg-info/requires.txt
rdsutilspack.egg-info/top_level.txt