Metadata-Version: 2.1
Name: rdsutilspack
Version: 2.0.0
Summary: My first Python package
Author: johnson
Author-email: johnssimon007@email.com
Classifier: Programming Language :: Python :: 3
Classifier: License :: OSI Approved :: MIT License
Classifier: Operating System :: OS Independent
